confiddler/__init__.py
confiddler/_version.py
confiddler/core.py
confiddler/json.py
confiddler/tests/__init__.py
confiddler/tests/test_core.py
confiddler/tests/test_json.py
confiddler-0.1.5.dist-info/LICENSE
confiddler-0.1.5.dist-info/METADATA
confiddler-0.1.5.dist-info/WHEEL
confiddler-0.1.5.dist-info/top_level.txt
confiddler-0.1.5.dist-info/RECORD
